CONTRIBUTORS.md
MANIFEST.in
NEWS.md
README.md
setup.cfg
setup.py
cdb_query/__init__.py
cdb_query/commands.py
cdb_query/commands_parser.py
cdb_query/core.py
cdb_query/logging_server.py
cdb_query/parsers.py
cdb_query/queues_manager.py
cdb_query.egg-info/PKG-INFO
cdb_query.egg-info/SOURCES.txt
cdb_query.egg-info/dependency_links.txt
cdb_query.egg-info/entry_points.txt
cdb_query.egg-info/not-zip-safe
cdb_query.egg-info/requires.txt
cdb_query.egg-info/top_level.txt
cdb_query/data/__init__.py
cdb_query/data/testing_data.py
cdb_query/data/testing_data_fx.py
cdb_query/nc_Database/__init__.py
cdb_query/nc_Database/db_manager.py
cdb_query/nc_Database/db_utils.py
cdb_query/netcdf4_soft_links/__init__.py
cdb_query/netcdf4_soft_links/netcdf4_soft_links/__init__.py
cdb_query/netcdf4_soft_links/netcdf4_soft_links/setup.py
cdb_query/netcdf4_soft_links/netcdf4_soft_links/netcdf4_soft_links/__init__.py
cdb_query/netcdf4_soft_links/netcdf4_soft_links/netcdf4_soft_links/certificates.py
cdb_query/netcdf4_soft_links/netcdf4_soft_links/netcdf4_soft_links/commands.py
cdb_query/netcdf4_soft_links/netcdf4_soft_links/netcdf4_soft_links/core.py
cdb_query/netcdf4_soft_links/netcdf4_soft_links/netcdf4_soft_links/parsers.py
cdb_query/netcdf4_soft_links/netcdf4_soft_links/netcdf4_soft_links/queues_manager.py
cdb_query/netcdf4_soft_links/netcdf4_soft_links/netcdf4_soft_links/requests_sessions.py
cdb_query/netcdf4_soft_links/netcdf4_soft_links/netcdf4_soft_links/retrieval_manager.py
cdb_query/netcdf4_soft_links/netcdf4_soft_links/netcdf4_soft_links/retrieval_utils.py
cdb_query/netcdf4_soft_links/netcdf4_soft_links/netcdf4_soft_links/data/__init__.py
cdb_query/netcdf4_soft_links/netcdf4_soft_links/netcdf4_soft_links/data/testing_data.py
cdb_query/netcdf4_soft_links/netcdf4_soft_links/netcdf4_soft_links/data/testing_data_fx.py
cdb_query/netcdf4_soft_links/netcdf4_soft_links/netcdf4_soft_links/ncutils/__init__.py
cdb_query/netcdf4_soft_links/netcdf4_soft_links/netcdf4_soft_links/ncutils/append.py
cdb_query/netcdf4_soft_links/netcdf4_soft_links/netcdf4_soft_links/ncutils/compare_dataset.py
cdb_query/netcdf4_soft_links/netcdf4_soft_links/netcdf4_soft_links/ncutils/core.py
