Metadata-Version: 1.1
Name: cdb-query
Version: 2.0
Summary: Simple tools to query and retrieve data from the ESGF's CMIP5 and CORDEX projects.
Home-page: UNKNOWN
Author: F. B. Laliberte
Author-email: frederic.laliberte@utoronto.ca
License: BSD
Keywords: atmosphere climate
Platform: UNKNOWN
Classifier: Development Status :: 5 - Production/Stable
Classifier: Operating System :: POSIX :: Linux
Classifier: Operating System :: MacOS :: MacOS X
Classifier: Intended Audience :: Science/Research
Classifier: Natural Language :: English
Classifier: License :: OSI Approved :: MIT License
Classifier: Programming Language :: Python :: 2.7
Classifier: Programming Language :: Python :: 3.4
Classifier: Programming Language :: Python :: 3.5
Classifier: Programming Language :: Python :: 3.6
Classifier: Topic :: Scientific/Engineering :: Atmospheric Science
Classifier: Topic :: Scientific/Engineering :: Mathematics
Classifier: Topic :: Scientific/Engineering :: Physics
